{"header":{"word":"תַּתְּנַי","entry":11529,"letter":"ת","strongs":8674,"page":1118},"definitions":[{"title":"Def","body":" &#134; [[תַּתְּנַי]] ","content":"definition","show":"block"},{"title":"n.pr.m.","body":" Pers. perfect. in Syria;&#8212;Ezr 5:3, Ezr 5:6, Ezr 6:6, Ezr 6:13; <span class=\"greek\">Qanqanav</span>, A <span class=\"greek\">Qaqqanai</span>; LXXL <span class=\"greek\">Tanqanaiov</span>, <span class=\"greek\">Sisinnhv</span>; also 3 Esdr 6:3, 7:26 Jos:Ant. xi. 12, 89, etc. (Lag:Psalt. Hieron.162 n.; AS:&#167;135 n.; Mey:Entst. J. 32 assumes OP * Thithnaya, or *Thathnaia); but U&#353;tanni, U&#353;tanu, was prefect in Syria under Darius, acc. to contr. tablets. v. Strassm:Darius 27, 82; names prob. identical; Meissn:ZAW xvii (1897), 191 f. reads therefore [[ושׁתני]] ([[וַשְׁתָּנִי]] Hpt), cf. Buhl Gu:Ezr-Ne 63; Scheft:94, however, thanks [[תתני]] = [[תסני]] OP th&#257;sna, Av. s&#257;sna (teaching), and this transp. in NBab. U&#353;tanu\r","content":"definition","show":"block"}],"notes":"","etymology":[],"morphology":[]}