{"header":{"word":"נֶ֫פֶשׁ","entry":6251,"letter":"נ","strongs":5315,"page":659},"definitions":[{"title":"Def","body":" [[נֶ֫פֶשׁ]]:756 ","content":"definition","show":"block"},{"title":"n. f.","body":":Ge 49:6 (so even Ge 2:19, Nu 31:28, 1Ki 19:2 v. Albrecht:ZAW xvi (1896), 42 SS) soul, living being, life, self, person, desire, appetite, emotion, and passion (Sir 3:18, Sir 4:1, Sir 4:1, Sir 4:2, Sir 4:2, Sir 13:12, Sir 14:11);&#8212;&#180;[[נ]] Ge 1:20 +; [[נׇ֑פֶשׁ]] Ge 37:21 +; sf. [[נַפְשִׁי]] Ge 12:13 +; pl. [[נְפָשׁוֹת]] Ez Eze 13:18 + 13 t.; [[נְפָשׁׂת]] Ex 12:4, Le 27:2; cstr. [[נַפְשׁוֹת]] Ge 36:6 + 4 t.; [[נַפְשׁׂת]] Le 21:11; [[נְפָשִׁים]] Ez Eze 13:20 (but rd. [[חָפְשִׁים]], v. Co Berthol Toy); sf. [[נַפְשׁוֹתָם]] 2Sa 23:17 +; [[נַפְשׁׂתָם]] Nu 17:3 +:&#8212;","content":"definition","show":"block"},{"title":"1.","body":" = that which breathes, the breathing substance or being = <span class=\"greek\">yuxh/</span>, anima, the soul, the inner being of man: ","content":"definition","show":"block"},{"title":"a.","body":" disting. fr. [[בָּשָׂר]]: [[מִנֶּפֶשׁ]] [[וְעַד בָּשָׂר]] Is 10:18; [[הַנֶּפֶשׁ עִם הַבָּשָׂר]] De 12:23; fr. [[שְׁאֵר]] Pr 11:17; fr. [[בֶּטֶן]] body Ps 31:10. ","content":"definition","show":"block"},{"title":"b.","body":" both the inner [[נפשׁ]] and the outer [[בשׂר]] are conceived as resting on a common substratum: [[אַךְ בְּשָׂרוֹ]] :[[עָלָיו יִכְאָָב וְנַפְשׁוֹ עָלָיו תֶּאֱבָֽל]] Job 14:22 only his flesh upon him is in pain, and his soul upon him mourneth; cf. Ps 42:5, Ps 42:7, Ps 131:2, Job 30:16, La 3:20 [v. [[עַל]] ","content":"definition","show":"block"},{"title":"1 d","body":"], all poetical (cf. ","content":"definition","show":"block"},{"title":"6 c","body":"). ","content":"definition","show":"block"},{"title":"c.","body":" &#180;[[נ]] departs at death and returns with life: [[וַיְתִי]] [[בְּחֵאת נַפְשָׁהּ כִּי מֵתָה]] Ge 35:18 (E) and it came to pass when her soul was going forth (for she died); [[נׇֽפְחָה נַפְשָׁהּ]] Je 15:9 she breathed out her soul, cf. 1Ki 17:21, 1Ki 17:22, Job 11:20, Job 31:39. ","content":"definition","show":"block"},{"title":"d.","body":" oft. desired that the [[נפשׁ]] may be delivered: fr. Sh&#8337;&#8217;&#244;l Ps 16:10, Ps 30:4, Ps 49:16, Ps 86:13, Ps 89:49, Pr 23:14; fr. [[שַׁחַת]], the pit of Sh&#8337;&#8217;&#244;l, Is 38:17, Job 33:18, Job 33:22, Job 33:28, Job 33:30. ","content":"definition","show":"block"},{"title":"2.","body":" The [[נפשׁ]] becomes a living being: by God's breathing [[נשׁמת חיים]] into the nostrils of its [[בשׂר]]; of man Ge 2:7 (J); by implication of animals also Ge 2:19 (J); so Ps 104:29, Ps 104:30 cf. Ps 66:9; man is [[נֶפֶשׁ חַיׇּה]], a living, breathing being Ge 2:7 (J); elsewh. [[נפשׁ חיּה]] alw. of animals Ge 1:20, Ge 1:24, Ge 1:30, Ge 9:12, Ge 9:15, Ge 9:16 (all P), Ez Eze 47:9; so [[נפשׁ החיּה]] Ge 1:21, Ge 9:10 (both P), Le 11:10, Le 11:46 (H); [[נפשׁ השׁרחת]] Le 11:46 (H); [[נפשׁ כל חי]] Job 12:10. [[נפשׁ]] is frequently used with the verb [[חיה]]: &#134; [[וחיתה נפשׁ]] Ge 12:13, Ge 19:20 (both J), 1Ki 20:32 (E), Ps 119:175, Je 38:17, Je 38:20; &#134; [[חֵי נַפְשְְׁ]] 1Sa 1:26, 1Sa 17:55, 1Sa 20:3, 1Sa 25:26, 2Sa 11:11, 2Sa 14:9, 2Ki 2:2, 2Ki 2:4, 2Ki 2:6, 2Ki 4:30 (all JE); cf. &#134; &#180;[[יְחַיֶּה נ]] 1Ki 20:31 (E), Ez Eze 18:27, Ps 22:30; also Ge 19:19, Is 55:3, Pr 3:22. ","content":"definition","show":"block"},{"title":"3.","body":" The [[נפשׁ]] (without [[חיה]] noun or verb) is specif.: ","content":"definition","show":"block"},{"title":"a.","body":" a living being whose life resides in the blood [so in Arab. We:Skizzen iii. 217 G. Jacob:Arab. Dicht. iv. 9 f.] (hence sacrificial use of blood, and its prohib. in other uses; first in D), De 12:23, De 12:24 only be sure that thou eat not the blood, for the blood is the living being ([[הַדָּם הוּא הַנֶּפֶשׁ]]); and thou shalt not eat the living being with the flesh ([[הַנֶּפֶשׁ עִם הַבָּשָׂר]]); thou shalt pour it upon the earth as water; this is enlarged in H, Le 17:10, Le 17:11, Le 17:12, Le 17:14 and in P Ge 9:4, Ge 9:5, cf. Je 2:34. ","content":"definition","show":"block"},{"title":"b.","body":" a serious attack upon the life is an attack upon this inner living being 2Sa 1:9, Je 4:10, Jon 2:6, Ps 69:2, Ps 124:4, Ps 124:5, Job 27:3. ","content":"definition","show":"block"},{"title":"c.","body":" [[נפשׁ]] is used for life itself 171 t., of animals Pr 12:10, and of man Ge 44:30 (J); [[נפשׁ תחת נפשׁ]] life for life Ex 21:23 (E), Le 24:18 (H), 1Ki 20:39, 1Ki 20:42, 2Ki 10:24; [[נפשׁנו תחתיכם]] Jos 2:14 (J); [[נפשׁ בנפשׁ]] De 19:21; [[בנפשׁ]] for the life of 2Sa 14:7 Jon 1:14; [[שׂם נפשׁ בכף]] put life in one's own hand Ju Jdg 12:3, 1Sa 19:5, 1Sa 28:21, Job 13:14; [[חרף נפשׁו]] [[למות]] Ju Jdg 5:18 risked his life to die; &#134; [[בנפשׁ]] at the risk of life Nu 17:3 (P), 2Sa 23:17 = 1Ch 11:19, 1Ch 11:19, 1Ki 2:23, Pr 7:23, La 5:9; &#134; [[בקּשׁ נפשׁ]] Ex 4:19 (J), 1Sa 20:21, 1Sa 22:23, 1Sa 22:23, 1Sa 23:15, 1Sa 25:29, 2Sa 4:8, 2Sa 16:11, 1Ki 19:10, 1Ki 19:14, Je 4:30, Je 11:21, Je 19:7, Je 19:9, Je 21:7, Je 22:25, Je 34:20, Je 34:21, Je 38:16, Je 44:30, Je 44:30, Je 46:26, Je 49:37, Ps 35:4, Ps 38:13, Ps 40:15, Ps 54:5, Ps 63:10, Ps 70:3, Ps 86:14, Pr 29:10; &#134; &#180;[[שׁאל נ]] 1Ki 3:11 = 2Ch 1:11, 1Ki 19:4 = Jon 4:8; &#134; [[הִכָּה נפשׁ]] smite mortally Ge 37:21 (J), De 19:6, De 19:11, Je 40:14, Je 40:15; &#134; &#180;[[לקח נ]] 1Ki 19:4, Jon 4:3, Ps 31:14, Pr 1:19; &#134; [[הִצִּיל]] [[נֶפֶשׁ מִמָּוֶת]] deliver life from death Jos 2:13, Ps 33:19, Ps 56:13; &#134; [[מלּט נפשׁ]]1Sa 19:11, 2Sa 19:6, 2Sa 19:6, 2Sa 19:6, 2Sa 19:6, 1Ki 1:12, 1Ki 1:12, Je 48:6, Je 51:6, Je 51:45, Ez Eze 33:5, Am 2:14, Am 2:15, Ps 89:49, Ps 116:4; &#134; [[פדה]] &#180;[[נ]] 2Sa 4:9, 1Ki 1:29, Ps 34:23, Ps 49:16, Ps 55:19, Ps 71:23; &#134; &#180;[[שׁמר נ]] Ps 25:20, Ps 97:10, Job 2:6, Pr 13:3, Pr 16:17, Pr 19:16, Pr 22:5. ","content":"definition","show":"block"},{"title":"4.","body":" The [[נפשׁ]] as the essential of man stands for  the man himself: ","content":"definition","show":"block"},{"title":" a.","body":" paraphrase for pers. pron. esp. in poetry and ornate discourse, 70t.; (1) [[נַפְשִׁי]] = me: [[אל תבא נפשׁי]] Ge 49:6 let me not enter (poem in J); [[מות ישׁרים]] &#180;[[תָּמׂת נ]] Nu 23:10 let me die, etc. (poem); [[תָּמוֹת נַפְשְׁי]] Ju Jdg 16:30 (J); [[אמרה נפשׁי]] La 3:24 I say. (2) [[נַפְשְְׁ]] = thee: [[לְאֻמִּים תַּחַת נַפְשְֶָׁ]] Is 43:4 peoples instead of thee; [[אָֽמְרוּ לְנַפְשֵׁךְ]] Is 51:23. (3) [[נַפְשׁוֹ]] = he: [[נפשׁו בטוב]] [[תלין]] Psalm he will not dwell in good circumstances. (4) [[נַפְשֵׁנוּ]] = we: [[נַפְשֵׁנוּ כְּחִפּוֹר נִמְלְטָה]] [[מִפַּח יוֹקְשִׁים]] Ps 124:7. (5) [[נַפְשָׁם]] = they, them: [[נַפְשָׁם בַּשְּׁבִי הָלָָכָה]] Is 46:2 they are gone into captivity; [[אוי לנפשׁם]] Is 3:9. ","content":"definition","show":"block"},{"title":"b.","body":" = reflexive, self, 53 t.: [[אסר על נפשׁ]] bind oneself Nu 30:3, Nu 30:5, Nu 30:5, Nu 30:6, Nu 30:7, Nu 30:8, Nu 30:9, Nu 30:10, Nu 30:11, Nu 30:12; &#180;[[לְעַנּׁת נ]] Nu 30:14 to afflict oneself . (1) [[נַפְשִׁי]] = myself: [[לא אדע נפשׁי]] Job 9:21 I know not myself. (2) [[נַפְשְְׁ]] = thyself: &#180;[[שׁמר נ]] De 4:9 keep thyself. (3) [[נַפְשׁוֹ]] = himself: &#180;[[אהב כנ]] 1Sa 18:1, 1Sa 18:3, 1Sa 20:17 loved as himself. (4) [[נַפְשָׁהּ]] = herself: &#180;[[חדּקה נ]] Je 3:1l justified herself. (5) [[נַפְשָׁם]] = themselves: &#180;[[החיל נ]] deliver themselves Is 47:14, Ez Eze 14:14, Eze 14:20. (6) [[נַפְשְׁכֶם]], [[נַפְשׁׂתֵיכֶם]] = yourselves: &#180;[[אַל־תַּשִּׁאוּ נ]] Je 37:9 deceive not yourselves, also Je 42:20, Je 44:7; &#180;[[ענּה נ]] Le 16:29, Le 16:31, Le 23:27, Le 23:32, Nu 29:7 (P); &#180;[[נשׁמרתם לנ]] De 4:15 Jos 23:11 (D). (7) [[נַפְשׁוֹתֵינוּ]] = ourselves: &#180;[[על נ]] Je 26:19  against ourselves. ","content":"definition","show":"block"},{"title":"c.","body":" = person of man, individual, 144 t., first in D:2; esp. in H, P, and kindred writers: (1) c. [[אָדָם]]: [[אדם]] &#180;[[נ]] Le 24:17 opp. [[בהמה]] &#180;[[נ]] Le 24:18 (both H), and so [[אדם]] &#180;[[נ]] human persons Nu 31:35, Nu 31:40, Nu 31:46 (P) 1Ch 5:21, Ez Eze 27:13. Elsewhere without [[אדם]]: [[ברכה]] &#180;[[נ]] Pr 11:25 one who blesses; [[רְמִיָּה]] &#180;[[נ]] Pr 19:15 idle person; &#180;[[תחת נ]] &#180;[[נ]] person in place of person, Job 16:4; [[כפּר]] &#180;[[על נ]] Ex 30:15, Ex 30:16, Nu 15:28, Nu 31:50 (all P) Le 17:11 (H). &#134; (2) [[נפשׁ]] = person, any one: De 24:7, De 27:25, Pr 28:17, Ez Eze 18:4, Eze 18:4, Eze 18:4, Eze 33:6; elsewhere only H P: Le 2:1, Le 4:2, Le 4:27, Le 5:1, Le 5:2, Le 5:4, Le 5:15, Le 5:17, Le 5:21, Le 7:18, Le 7:20, Le 7:21, Le 7:25, Le 7:27, Le 23:29, Le 23:30, Le 23:30, Nu 5:6, Nu 15:27, Nu 15:30, Nu 19:22, Nu 31:19, Nu 31:28, Nu 35:11, Nu 35:15, Nu 35:30, Nu 35:30, Jos 20:3, Jos 20:9 (all P), Le 17:10, Le 17:12, Le 17:15, Le 20:6, Le 20:6, Le 22:6, Le 22:11 (all H); &#180;[[נכרתה הנ]] [[הַהִוא מן]] that person shall be cut off from: only in Ge 17:14, Ex 12:15, Ex 12:19, Ex 31:14, Le 7:20, Le 7:21, Le 7:27, Nu 9:13, Nu 15:30, Nu 15:31, Nu 19:13, Nu 19:20 (all P), Le 19:8, Le 22:3 (both H). &#134; (3) [[נפשׁ]] coll. for persons, in enumerations: De 10:22, Jos 10:28, Jos 10:30, Jos 10:32, Jos 10:35, Jos 10:37, Jos 10:37, Jos 10:39, Jos 11:11 (all D:2) Je 43:6, Je 52:29, Je 52:30, Je 52:30, Ez Eze 22:25; elsewhere only Ge 12:5, Ge 46:15, Ge 46:18, Ge 46:22, Ge 46:25, Ge 46:26, Ge 46:26, Ge 46:27, Ge 46:27, Ex 1:5, Ex 1:5, Ex 12:16, Nu 31:35, Nu 31:40 (all P). &#134; (4) [[נְפָשׁוֹת]] persons Ge 36:6, Ex 12:4, Ex 16:16, Nu 19:18 (all P), Le 18:29, Le 20:25, Le 27:2 (all H), 2Ki 12:5, Pr 11:30, Pr 14:25, Ez Eze 13:18, Eze 13:18, Eze 13:18, Eze 13:19, Eze 13:19, Eze 13:20, Eze 13:20, Eze 17:17, Eze 18:4, Eze 22:27 ([[נפשׁים]] Eze 13:20 v. supr.). &#134; (5) [[נפשׁ]] = deceased person, sts. c. [[מֵת]], [[נֶפֶשׁ מֵת]] Nu 6:6 (P), [[נַפְשׁׂת מֵת]] (LXX SyrVer [[נֶפֶשׁ]]) Le 21:11 (H); usu. without [[מֵת]], [[אדם]]([[ה]])[[נפשׁ ]] Nu 9:6, Nu 9:7, Nu 19:11, Nu 19:13 (P); or simply [[נפשׁ]], Le 19:28, Le 21:1, Le 22:4 (all H) Nu 5:2, Nu 6:11, Nu 9:10 (all P); elsewhere only Hag 2:13. ","content":"definition","show":"block"},{"title":"5.","body":" [[נפשׁ]] = seat of the appetites, in all periods (46 t.)&#8212;","content":"definition","show":"block"},{"title":"a.","body":" hunger: [[רְעֵבָה]] &#180;[[נ]] hungry soul Ps 107:9, Pr 27:7; with noun or verb of [[שׂבע]] satisfy Is 56:11, Is 58:10, Je 50:19, Ez Eze 7:19, Ps 63:6, Ps 107:9, Pr 13:25, Pr 27:7; &#180;[[מתוק לנ]] Pr 16:24 sweet to the taste. ","content":"definition","show":"block"},{"title":"b.","body":" thirst: [[עֲיֵפָה]] &#180;[[נ]] weary soul Pr 25:25, Je 31:25; [[כארץ עיפה]] &#180;[[נ]] Ps 143:6; &#180;[[חמאה נ]] Ps 42:3, Ps 63:2. ","content":"definition","show":"block"},{"title":"c.","body":" appetite in general: [[יַקִּיפוּ עָלָיו]] &#180;[[אׂיְבַי בנ]] Ps 17:9 my enemies compass me about with greed; [[הִרְחִיבָה שְׁאוֹל נַפְשָׁהּ וּפָֽעֲרָה פִיהָ]] Is 5:14 Sh&#8337;&#8217;&#244;l enlarged her appetite, etc., cf. Hb Hab 2:5; Pr 23:2 [[בַּעַל נֶפֶשׁ]]; Ec uses [[נפשׁ]] only in the sense of ","content":"definition","show":"block"},{"title":"a, b, c","body":"; the [[נפשׁ]] craves, lacks, and is filled with good things: Ec 2:24, Ec 4:8, Ec 6:2, Ec 6:3, Ec 6:7, Ec 6:9, Ec 7:28. ","content":"definition","show":"block"},{"title":"6.","body":" = &#180;[[נ]] seat of emotions and passions (151 t.)&#8212;","content":"definition","show":"block"},{"title":" a.","body":" desire: &#134; &#180;[[אִוְּתָה נ]] soul desires De 12:20, De 14:26, 1Sa 2:16, 2Sa 3:21, 1Ki 11:37, Job 23:13, Pr 13:4, Pr 21:10, Mic 7:1; &#180;[[תַּאֲוַת נ]] Ps 10:3, Is 26:8; &#134; &#180;[[אַוַּת נ]] De 12:15; De 12:20; De 12:21, De 18:6, 1Sa 23:20, Je 2:24; so also [[לנפשׁ]] according to one's desire De 21:14, Ps 78:18, Je 34:16; [[כנפשׁ]] De 23:25; [[האח נפשׁנו]] ah, our desire Ps 35:25; [[בנפשׁ]] at one's desire Ps 105:22, Ez Eze 16:27; [[יׇֽחְאָה]] &#180;[[נ]] [[בְדַבְּרוֹ]] Ct So 5:6; &#180;[[נשׂא נ]] lift up the soul, desire De 24:15, 2Sa 14:14 (rd. [[אליהם]], not [[אלהים]]), Ps 24:4, Ps 25:1, Ps 86:4, Ps 143:8, Pr 19:8, Je 22:27, Je 44:14, Ho 4:8. &#134; ","content":"definition","show":"block"},{"title":"b.","body":" abhorrence, loathing: &#180;[[געלה נ]] soul abhorreth Le 26:11, Le 26:15, Le 26:30, Le 26:43 (H) Je 14:19; [[בחלה בי]] &#180;[[וגם נ]] Zec 11:8 and their soul also fell a loathing against me. ","content":"definition","show":"block"},{"title":"c.","body":" sorrow and distress: &#134; &#180;[[מרי נ]] bitter, gloomy, discontented of soul Ju Jdg 18:25 (E) 2Sa 17:8, Job 3:20, Pr 31:6; &#134; &#180;[[מר נ]] 1Sa 22:2 cf. Job 7:11, Job 10:1, Is 38:15, Ez Eze 27:1; &#180;[[עָֽגְמָה נ]] Job 30:35 grieved; &#180;[[אגמי נ]] sad of soul Is 19:10; &#180;[[תבכה נ]] my soul shall weep Je 13:17; [[ירעה]] &#180;[[נ]] his soul trembleth Is 15:4; &#180;[[חרת נ]] distress of soul Ge 42:21 (E). &#134; ","content":"definition","show":"block"},{"title":"d.","body":" joy: [[תגיל]] &#180;[[נ]] my soul rejoiceth Ps 35:9, Is 61:10; &#180;[[שׂמּח נ]] rejoice the soul Ps 86:4; also Ps 94:19, Ps 138:3, Pr 29:l7. &#134; ","content":"definition","show":"block"},{"title":"e.","body":" love: &#180;[[אהבה נ]] my soul loveth Ct So 1:7, So 3:1, So 3:2, So 3:3, So 3:4; &#180;[[יְדִדוּת נ]] darling of my soul Je 12:7; &#180;[[ב]] &#180;[[דבקה נ]] his soul clave unto Ge 34:3 (J), c. [[אחרי]] Ps 63:9; [[חשׁקה]] &#180;[[ב]] &#180;[[נ]] soul is attached to Ge 34:8 (P). ","content":"definition","show":"block"},{"title":"f.","body":" alienation, hatred, revenge: &#134; [[מן]] &#180;[[תֵּקַע נ]] the soul is alienated from Je 6:8, Ez Eze 23:17, Eze 23:18; [[מן]] &#180;[[נקעה נ]] Ez Eze 23:18, Eze 23:22, Eze 23:28; &#180;[[שְׂנֻאי נ]] hated of soul 2Sa 5:8 (Qr); &#180;[[שׂנאה נ]] Ps 11:5, Is 1:14. ","content":"definition","show":"block"},{"title":" g.","body":" other emotions and feelings: &#180;[[השׁיב נ]]  bring back soul La 1:11, La 1:19 (i.e. revive, cf. c. [[שׁוּב]] 1Ki 17:21 f.), hence fig.  refresh, cheer, v:1Ki 17:16, Ps 19:8, Pr 25:14, Ru 4:15; &#180;[[שׁובב נ]] Ps 23:3; &#180;[[מַחְמַל נ]] your souls' compassion  Ez Eze 24:21; &#180;[[קחרה נ]] soul was impatient Nu 21:4 (E), Ju Jdg 10:16, Jdg 16:16, Zec 11:8; [[כי]] &#180;[[אאריך נ]] that I should prolong my patience Job 6:1l [[הגר]] &#180;[[ידעתם את־נ]] ye know the feeling of the stranger Ex 23:9 (R:D).\r","content":"definition","show":"block"},{"title":"7.","body":" [[נפשׁ]] is used occasionally for mental acts + [[לבב]] (see ","content":"definition","show":"block"},{"title":"10","body":"); poss. also alone, owing to unconscious assimilation by late writers; but most, if not all, exx. may be otherwise explained: [[נפשׁי ידעת מאד]] Ps 139:14 my soul knoweth well (or I know well; cf. ","content":"definition","show":"block"},{"title":"4a","body":"); [[בלא]] [[לא טוב]] &#180;[[דעת נ]] Pr 19:2 that the soul be without knowledge is not good (but RV:m desire without knowledge, cf. ","content":"definition","show":"block"},{"title":"6 a","body":"); &#180;[[דעה חכמה לנ]] Pr 24:14 know wisdom for thy soul (or  according to thy desire, cf.","content":"definition","show":"block"},{"title":" 6 a","body":"); &#180;[[אל תדמי בנ]] Es 4:13 think not in thy soul (or in thyself, cf. ","content":"definition","show":"block"},{"title":"4 b","body":"); [[כמו שׁער]] &#180;[[בג]] Pr 23:7 as he reckoneth in his soul (but RV in himself, cf. ","content":"definition","show":"block"},{"title":"4 b","body":"); &#180;[[מה תאמר נ]] 1Sa 20:4 (but AV RV foll. LXX <span class=\"greek\">e)piqumei=</span> = [[תְּאַוֶּה]]; v. ","content":"definition","show":"block"},{"title":"6 a","body":" ).\r","content":"definition","show":"block"},{"title":"8.","body":" [[נפשׁ]] for acts of the will is dub.: [[אם ישׁ]] [[נפשׁכם]] ([[את]]) if it is your purpose Ge 23:8 (P) 2Ki 9:15 (or if it is your desire, ","content":"definition","show":"block"},{"title":"6 a","body":"); &#180;[[בחרה נ]] my soul chooseth Job 7:l5; &#180;[[מאנה נ]] my soul, re-fuseth Job 6:7, Ps 77:3; [[חפחה]] &#180;[[נ]] their soul delighteth in Is 66:3; [[רחתה]] &#180;[[נ]] my soul delighteth in Is 42:1; (all perhaps emotional, ","content":"definition","show":"block"},{"title":"6 b, d, g","body":").\r","content":"definition","show":"block"},{"title":"9.","body":" [[נפשׁ]] = character is still more dub.: [[בּוֹ]] &#180;[[לאׂ־יָֽשְׁרָה נ]] Hb Hab 2:4 his soul is not right in him (but LXX <span class=\"greek\">ou)k eu)dokei= h( yuxh/ mou e)n au)tw=| )/eu)dokei=</span> = [[רחתה]]], v.","content":"definition","show":"block"},{"title":"6.","body":"); [[נַפְשִׁי לאׂ מְטֻמָּאָה]] Ez Eze 4:14 my soul hath not  (or I have not, ","content":"definition","show":"block"},{"title":"4 a","body":") been polluted.\r","content":"definition","show":"block"},{"title":"Def","body":"&#134;","content":"definition","show":"block"},{"title":"10.","body":" &#180;[[נ]]in D, when used with [[לבב]], is assim. to it, and shares with it the mngs. of ","content":"definition","show":"block"},{"title":"7, 8, 9","body":"; and so in later writers influenced by D (unless we may think that &#180;[[ל]] is used of intellect, while &#180;[[נ]] is used of the feelings): thus, [[בכל לבב]] [[ובכל נפשׁ]] (see [[לבב]]): c. [[דרשׁ]] De 4:29, 2Ch 15:12; [[עשׂה]] De 26:16; [[אהב]] De 6:5, De 13:4, De 30:6; [[ידע]] Jos 23:14; [[עבד]] De 10:12, De 11:13, Jos 22:5; [[שׁמע בקלו]] De 30:2; [[שׁוב אל]] De 30:10, 1Ki 8:48 = 2Ch 6:38, 2Ki 23:25; [[שׁמר מחות]] 2Ki 23:3 = 2Ch 34:31; [[הלך לפני]]1Ki 2:4; and De 11:18, 1Sa 2:35, 1Ch 22:19, 1Ch 28:9, Je 32:41, Ps 13:8, Pr 2:10, Pr 24:12. Note.&#8212;In three cases is generally found closer approach to supposed radical meaning breath:&#8212;","content":"definition","show":"block"},{"title":"a.","body":" [[שׁמן וקטרת ישׂמח לב ומתק]] [[רעהו מעחת נפשׁ]] Pr 27:9. Ges (after D&#246;derlein) renders a. &#180;[[מעחת נ]] more than odorous trees, so later edds., even Buhl; but Vulgate De SS transp.) [[מֵעֲחַת רֵעֵהוּ]] &#180;[[וּמֶתֶק נ]]. LXX Hi Bi [[ומתקרעה]] = the soul is rent asunder by cares. In any case [[נפשׁ]]is &#8214;[[לב]], cf. ","content":"definition","show":"block"},{"title":"10. b.","body":" [[נַפְשׁוֹ גֶּחָלִים תְּלַהֵט]] Job 41:13 his breath kindleth coals (of the crocodile).The piece is one of the latest in the book; primitive meaning hardly in such a passage; context favours ref. to passion or fury; perhaps sub ","content":"definition","show":"block"},{"title":"6 f,","body":" his passion or fury kindleth coals. ","content":"definition","show":"block"},{"title":"c.","body":" [[בָּתֵּי הַנֶּפֶשׁ]] Is 3:20 perfume boxes; mng. evident from context; but not necessarily scent (breath)-boxes; may be ","content":"definition","show":"block"},{"title":"6 a,","body":" boxes of desire, or ","content":"definition","show":"block"},{"title":"5,","body":"  boxes exciting the sense of smell; = smelling boxes or bottles. No sufficient evid. in BH, therefore, for meaning breath, odour.&#8212;See, for complete study of [[נֶפֶשׁ]] (all passages), Br:JBL l897,17 ff.\r","content":"definition","show":"block"}],"notes":"","etymology":[],"morphology":[]}