{"header":{"word":"[טָפַף","entry":3712,"letter":"ט","strongs":2952,"page":381},"definitions":[{"title":"Def","body":" &#134; [[[טָפַף]]] ","content":"definition","show":"block"},{"title":"vb.","body":" trip, take quick little steps (cf. Ar. t.af=a pass by quickly, t.af=a0fun light, brisk, quick, of horse; poss. cf. Syr. t.apt.ep flicker)&#8212;","content":"definition","show":"block"},{"title":"Qal","body":" Inf. abs. [[טָפׂף]] Is 3:16 [[הָלוֹךְ וְטָפׂף תֵּלַכְנׇה]], of women of Jerusalem.\r","content":"definition","show":"block"}],"notes":"","etymology":[],"morphology":[]}