{"header":{"word":"גֶּ֫בֶא","entry":1568,"letter":"ג","strongs":1360,"page":146},"definitions":[{"title":"Def","body":" &#134; [[גֶּ֫בֶא]] ","content":"definition","show":"block"},{"title":"n.m.","body":":Ez Eze 47:11 cistern, pool (cf. Ar. ja0biyah;un watering-trough)&#8212;","content":"definition","show":"block"},{"title":"1.","body":" cistern [[מַיִם מִגֶּ֑בֶא]] Is 30:14. ","content":"definition","show":"block"},{"title":"2.","body":" pool, marsh [[גְּבָיׇאו]] Ez Eze 47:11 (&#8214;[[כִּצּאׁתָ֠ו]]).\r","content":"definition","show":"block"}],"notes":"","etymology":[],"morphology":[]}