{"header":{"word":"פֶּ֫תִי","entry":7933,"letter":"פ","strongs":6612,"page":834},"definitions":[{"title":"Def","body":" &#134;[[פֶּ֫תִי]] [for [[פָּתַי]] Lag BN 52 Ba:ZMG xlii (1888), 353; NB 320] ","content":"definition","show":"block"},{"title":"adj.","body":" simple, poss. as open-minded;&#8212;[[פֶּ֫תִי]] Pr 9:4 +, [[פֶָּתִי]] Ps 19:8 +; pl. [[פְּתָאיִם]] (Ges:&#167; 93 x) Ps 116:6 + 6 t. Pr; [[פְּתָיִים]] Ps 119:130, Pr 22:3; [[פְּתָיִם]] Pr 1:22, Pr 1:32; &#8212;simple, as subst. concr.: open to the instruction of wisdom or folly, Pr 9:4, Pr 9:16; believing every word Pr 14:15; lacking [[עָרְטָה]] Pr 1:14, Pr 8:5, Pr 19:25; needing [[בין]] Ps 119:130, [[חכטה]] Ps 19:8, Pr 21:11; in good sense, [[שׁמר]] &#180;[[פתאים י]] Ps 116:8 &#180;[[י]] preserveth ths simple-minded; but usu. tendency to bad sense ; [[פתאים]] love [[פתי]] Pr 1:22; inherit [[אִוֶּלֶת]] Pr 14:18, are easily enticed, misled and go back Pr 1:32, Pr 7:7, Pr 9:6, Pr 22:3 = Pr 27:12; they need atonement Ez Eze 45:20 (&#8214;[[שׁגה ]]).\r","content":"definition","show":"block"}],"notes":"","etymology":[],"morphology":[]}