{"header":{"word":"אַדֶּ֫רֶת","entry":161,"letter":"א","strongs":155,"page":12},"definitions":[{"title":"Def","body":" &#134; [[אַדֶּ֫רֶת]] ","content":"definition","show":"block"},{"title":"n.f.","body":" glory, cloak&#8212;&#180;[[א]] abs. Jos 7:24; [[אַדָָּרֶת]] Ez Eze 17:8; cstr. Ge 25:25 + 4 t.; [[אַדַּרְתּוֹ]] 1Ki 19:13 + 3 t.; [[אַדַּרתָּם]] Zec 11:3&#8212;","content":"definition","show":"block"},{"title":"1.","body":" glory, magnificence, of vine Ez Eze 17:8 (so Thes MV, but &#60; adj. f. fr. [[אַדִּיר]] q.v.), of shepherds Zec 11:3 (or sub ","content":"definition","show":"block"},{"title":"2","body":"). ","content":"definition","show":"block"},{"title":"2.","body":" mantle, cloak (wide garment) of hair [[שֵׂעָר]] Ge 25:25, Zec 13:4 (as proph. mantle, so perh. Zec 11:3 of shepherds = false proph.) cf. of Elijah 1Ki 19:13, 1Ki 19:19, 2Ki 2:8, 2Ki 2:13, 2Ki 2:14; but [[אַדֶּרֶת שִׁנְעָר טוֹבָה]] (fine mantle of Shinar = Babylonian mantle&#8212;doubtless costly) Jos 7:21, Jos 7:24 (J) &#38; (late) &#180;[[א]] alone Jon 3:6.\r","content":"definition","show":"block"}],"notes":"","etymology":[],"morphology":[]}