{"header":{"word":"חַגַּי","entry":2821,"letter":"ח","strongs":2292,"page":291},"definitions":[{"title":"Def","body":" &#134; [[חַגַּי]] ","content":"definition","show":"block"},{"title":"n.pr.m.","body":" (festal; Ph. [[חגי]], [[חגת]]; Palm. [[חגגו]] Vog:No. 61)&#8212;the prophet Haggai Hag 1:1, Hag 1:3, Hag 1:12, Hag 1:13, Hag 2:1, Hag 2:10, Hag 2:13, Hag 2:14, Hag 2:20, Ezr 5:1, Ezr 6:14; LXX <span class=\"greek\">)Aggai=ov</span>.\r","content":"definition","show":"block"}],"notes":"","etymology":[],"morphology":[]}