{"header":{"word":"עַלְוׇן","entry":7105,"letter":"ע","strongs":5935,"page":759},"definitions":[{"title":"Def","body":" &#134; [[עַלְוׇן]] ","content":"definition","show":"block"},{"title":"n.pr.m.","body":" in Edom Ge 36:23 (P), LXX <span class=\"greek\">Gwlwn</span>, <span class=\"greek\">Gwlam</span> = 1Ch 1:40 Qr (Kt [[עלין]]), LXX <span class=\"greek\">Swlam</span>, A <span class=\"greek\">Iwlam</span>, LXXL <span class=\"greek\">Alouan</span>.\r","content":"definition","show":"block"}],"notes":"","etymology":[],"morphology":[]}