{"header":{"word":"בִּירָה","entry":1157,"letter":"ב","strongs":1002,"page":108},"definitions":[{"title":"Def","body":" &#134; [[בִּירָה]] ","content":"definition","show":"block"},{"title":"n.f.","body":" castle, palace (late &#38; prob. loan-word; cf. As b&#238;rtu, fortress Dl:HA 22; Pers. b&#226;ru = Skr. bura, bari, v. Ry Ne 2:8)&#8212;","content":"definition","show":"block"},{"title":"1.","body":" of temple at Jerusalem 1Ch 29:1, 1Ch 29:19 [[הַבִּירָת]]; of for-tress near temple Ne 2:8, Ne 7:2 (cf. <span class=\"greek\">ba=riv</span> LXXL Ne 1:1, Ne 2:8, Ne 7:2&#8212;B <span class=\"greek\">a(bira/</span>, <span class=\"greek\">beira/</span>&#8212;and later <span class=\"greek\">ba=riv</span> Jos:Ant. xv. 11, 4). ","content":"definition","show":"block"},{"title":"2.","body":" [[בְּשׁוּשַׁן הַבִּירָה]] Ne 1:1, Es 1:2, Es 1:5, Es 2:3, Es 2:5, Es 2:8, Es 3:15, Es 8:14, Es 9:6, Es 9:11, Es 9:12, Da 8:2; in these passages it appar. means a fortress in the city bearing the same name (cf. esp. Es 3:15, Es 8:14, Es 8:15, Es 9:6, Es 9:12, Es 9:15, Es 9:18).\r","content":"definition","show":"block"}],"notes":"","etymology":[],"morphology":[]}