{"header":{"word":"שָׂבְעָה","entry":9348,"letter":"שׂ","strongs":7653,"page":960},"definitions":[{"title":"Def","body":" &#134; [[שָׂבְעָה]], [[[שִׂבְעָה]]] ","content":"definition","show":"block"},{"title":"n.f.","body":" satiety;&#8212;abs. &#180;[[שׂ]]: Is 56:11 +, cstr. [[שִׂבְעַת־]] Ez Eze 16:49, sf, [[שָׂבְעָתַח]] v:Eze 16:28;&#8212;","content":"definition","show":"block"},{"title":"1.","body":" as to food, esp. &#180;[[אָכַל לְשׂ]]: eat to satiety, one&#8217;s fill, Is 23:18, Ez Eze 39:19; &#180;[[לְשׂ]]: also Is 55:2 (fig.); &#180;[[שׂ]]: of dogs Is 56:11 (fig.); [[־לֶחֶםָ]]&#180;[[שׂ]]: leading to arrogance, as sin of Sodom Ez Eze 16:49 (+ [[גׇּאוֹם]], etc.). ","content":"definition","show":"block"},{"title":"2.","body":" to carnal desire Ez Eze 16:28 (fig.).\r","content":"definition","show":"block"}],"notes":"","etymology":[],"morphology":[]}