{"header":{"word":"[גּוּר","entry":1737,"letter":"ג","strongs":1481,"page":158},"definitions":[{"title":"Def","body":" &#134;III. [[[גּוּר]]] ","content":"definition","show":"block"},{"title":"vb. dread","body":" (cf. [[יׇגׁר]])&#8212;","content":"definition","show":"block"},{"title":"Qal","body":" Impf. [[וַיׇּגׇר]] Nu 22:3, 1Sa 18:15; 2 ms. [[תָּגוּר]] De 18:22; [[אָגוּר]] De 32:27; pl. [[יׇגוּרוּ]] Ps 33:8, Job 41:17 + Ho 10:5, [[תָּגוּרוּ]] De 1:17; Imv. [[גּוּרוּ]] Ps 22:24, Job 19:29; &#8212;","content":"definition","show":"block"},{"title":"1.","body":" be afraid of, sq. [[מִפְּנֵי]] Nu 22:3, De 1:17, 1Sa 18:15, [[גּוּרוּ לָכֶם מִפְּנֵי]] Job 19:29; c. [[מִן]] Job 41:17, De 18:22; c. acc. De 32:27 (poet.) Ho 10:5 rd. prob. [[ינודו]] lament (&#8214;[[אבל]], used c. [[לְ]] e.g. Na 3:7, Je 15:5 al.; cf. Che). ","content":"definition","show":"block"},{"title":"2.","body":" stand in awe of, sq. [[מִן]] Ps 22:24, Ps 33:8 ([[יׇרֵא]]).\r","content":"definition","show":"block"}],"notes":"","etymology":[],"morphology":[]}