{"header":{"word":"סִכּוּת","entry":6537,"letter":"ס","strongs":5522,"page":696},"definitions":[{"title":"Def","body":" &#134; [[סִכּוּת]] ","content":"definition","show":"block"},{"title":"n. pr. div.","body":" Am 5:26 read prob. &#133;[[סַכּוּת]], = As. Sakkut (epithet of Adar-Ninip = Saturn), Schr:SK 1874, 332; COT AM 5, 26, cf. Tiele:Gesch. 528 Bae:Rel 239 Rogers:Ency. Bib. 749 (Vrss Thes al. = [[סֻכָּה]], [[סֻכּוֹת]]).\r","content":"definition","show":"block"}],"notes":"","etymology":[],"morphology":[]}