{"header":{"word":"[יָנׇה","entry":3979,"letter":"י","strongs":3238,"page":413},"definitions":[{"title":"Def","body":" &#134; [[[יָנׇה]]] ","content":"definition","show":"block"},{"title":"vb.","body":" suppress (?), ","content":"definition","show":"block"},{"title":"oppress, maltreat","body":" (NH Hiph. vex with words; so Aram. Aph. [[אוֹנִי]], but also Targum for Heb. [[הוֹנׇה]] maltreat; Ar. wanay is laxus, debilis fuit, IV. debilitavit, defatigavit, but connex. dub.)&#8212;","content":"definition","show":"block"},{"title":"Qal","body":" Impf. 1 pl. sf. [[נִינׇם]] Ps 74:8; Pt. [[יוֹנׇה]] Je 25:38 + 3 t. + Ps 123:4 (v. infr.);&#8212;suppress (?) sq. acc. Ps 74:8 (text dub.); elsewhere oppress; Pt. abs. as adj. [[הָעִיר הַיּוֹנׇה]] Zep 3:1; subst. f. coll. [[הַיּוֹנׇה]] oppressors Je 25:38 (but rd. [[חֶרֶב]] for [[חֲרוֹן]], with LXX Ew Hi Gf Ke etc., as Je 46:16, Je 50:16); Ps 123:4 Qr [[לִגְאֵי יוֹנִים]] proudest oppressors (st. cstr. in superlat., cf. Ges:&#167; 133, 3, R. 1; yet most follow Kt [[לּגּאייונים]], and der. from [[גַּאֲיוֹן]] q.v. p. 145 supr.) ","content":"definition","show":"block"},{"title":"Hiph.","body":" Pf. [[הוֹנׇה]] Ez Eze 18:12, Eze 18:16; [[הוֹנוּ]] Eze 22:7, Eze 22:29; Impf. [[יוֹנֶה]] Eze 18:7; 2 ms. [[תּיׁנֶה]] Ex 22:20; [[תּוֹנֶנּוּ]] De 23:17; [[יוֹנוּ]] Ez Eze 45:8; [[תּוֹנוּ]] Le 19:33 + 2 t.; [[תּׂנוּ]] Je 22:3; Inf. sf. [[הוֹנׁתָם]] Ez Eze 46:18; Pt. [[מוֹנַ֫יִךְ]] Is 49:26; &#8212;oppress, maltreat, sq. acc., esp. of ill-treatment of poor and weak, partic. of the [[גֵּר]], the &#8216;stranger,&#8217; sojourner, by the rich and powerful, Ex 22:20 (JE), Le 19:33, Le 25:14, Le 25:17 (H), De 23:17, Je 22:3, Ez Eze 18:7, Eze 18:12, Eze 18:16, Eze 22:7, Eze 22:29, Eze 45:8, Eze 46:18; of a foreign oppressor only Is 49:26.\r","content":"definition","show":"block"}],"notes":"","etymology":[],"morphology":[]}