{"header":{"word":"שׁוּחַ","entry":9772,"letter":"שׂ","strongs":7744,"page":1001},"definitions":[{"title":"Def","body":" &#134; [[שׁוּחַ]] ","content":"definition","show":"block"},{"title":"n.pr.m.","body":" son of Abr. and &#7730;eturah, Ge 25:2, 1Ch 1:32; <span class=\"greek\">Swue</span>, <span class=\"greek\">Swe</span>, <span class=\"greek\">Soue</span>.&#8212;In As. &#352;u&#7723;i is named as Aramaean land on Euphr. (left bank Tiele:Gesch. 153 &#60; right bank, cf. esp. Schr:KG 142 f.; it had, however, dependencies on left bank) by TP I. (KB:i. 33), A&#353;urna&#7779;irp. (Id.:ib. 99, 101).\r","content":"definition","show":"block"}],"notes":"","etymology":[],"morphology":[]}