{"header":{"word":"[עָרַב","entry":7401,"letter":"ע","strongs":6150,"page":788},"definitions":[{"title":"Def","body":" &#134; [[[עָרַב]]] ","content":"definition","show":"block"},{"title":"vb. denom.","body":" become evening; grow dark (?);&#8212;","content":"definition","show":"block"},{"title":"Qal.","body":" Inf. cstr. [[רָפָה הַיּוֹם לַעֲרוֹב]] Ju Jdg 19:9, but rd. prob. [[נׇטָה הַיּוֹם לַעֶרֶב]] LXXL GFM; Pf. 3 fs. fig. [[עָֽרְבָה]] Is 24:11 all joy has grown dark, but rd. [[עָֽבְרָה]] has passed away Lo Gr Perles:Anal. 91 Che:Hpt al. ","content":"definition","show":"block"},{"title":"Hiph.","body":" Inf. abs. [[הַשְׁכֵּם]] [[וְהַעֲרֵב]] 1Sa 17:16 doing it at morning and at evening.\r","content":"definition","show":"block"}],"notes":"","etymology":[],"morphology":[]}