{"header":{"word":"אֲבִישׁוּעַ","entry":42,"letter":"א","strongs":50,"page":4},"definitions":[{"title":"Def","body":" &#134; [[אֲבִישׁוּעַ]] ","content":"definition","show":"block"},{"title":"n.pr.m.","body":" (my father is rescue, or is opulence (cf. [[שׁוֹעַ]] rich Job 34:19; also [[שׁוּעַ]] Job 36:19 ? but v. [[שׁוע]]); Lag:BN 75 thinks fr. [[אֲבֶן]] (= [[בֶּן]]) + [[שׁוע]] cf. LXX <span class=\"greek\">)Abessoue</span> 1Ch 8:4) ","content":"definition","show":"block"},{"title":"1.","body":" a son of Phinehas 1Ch 5:30, 1Ch 5:31, 1Ch 6:35, Ezr 7:5. ","content":"definition","show":"block"},{"title":"2.","body":" a Benjamite, son of Bela 1Ch 8:4.\r","content":"definition","show":"block"}],"notes":"","etymology":[],"morphology":[]}