{"header":{"word":"עֲשָׂיׇה","entry":7472,"letter":"ע","strongs":6222,"page":795},"definitions":[{"title":"Def","body":" &#134; [[עֲשָׂיׇה]] ","content":"definition","show":"block"},{"title":"n.pr.m.","body":" <span class=\"greek\">Asaiav</span>, etc.; LXXL in Kgs. <span class=\"greek\">Azariav</span>;&#8212;","content":"definition","show":"block"},{"title":"1.","body":" servant of Josiah 2Ki 22:12, 2Ki 22:14 = 2Ch 34:20. ","content":"definition","show":"block"},{"title":"2.","body":" Simeonite 1Ch 4:36. ","content":"definition","show":"block"},{"title":"3.","body":" Levites: ","content":"definition","show":"block"},{"title":"a.","body":" 1Ch 6:15, 1Ch 15:6, 1Ch 15:11. ","content":"definition","show":"block"},{"title":"b.","body":" 1Ch 9:5.\r","content":"definition","show":"block"}],"notes":"","etymology":[],"morphology":[]}