{"header":{"word":"נׇאַץ","entry":5828,"letter":"נ","strongs":5006,"page":610},"definitions":[{"title":"Def","body":" &#134; [[נׇאַץ]] ","content":"definition","show":"block"},{"title":"vb.","body":" contemn, spurn (NH id., Pi.; Targum [[נִיאוּחָא]] reviling);&#8212;","content":"definition","show":"block"},{"title":"Qal","body":" Pf. &#180;[[נ]] Pr 5:12; 3 pl. [[נָֽאֲחוּ]] Pr 1:30; [[נׇאָָחוּ]] Ps 107:11; Impf. [[יִנְאַץ]] Pr 15:5; [[יִנְאָחָוּן]] Je 33:24, etc.;&#8212;contemn, subj. wicked and foolish, obj. [[תּוֹכַחַת]] Pr 1:30, Pr 5:12; obj. [[מוּסָד]] Pr 15:5; [[עֵחָה]] Ps 107:11; Je 33:24 (obj. &#180;[[עַם י]]; cf. Gie); subj. &#180;[[י]] De 32:19, Je 14:21, La 2:6. ","content":"definition","show":"block"},{"title":"Pi.","body":" Pf. [[נִאֵץ]] Ps 10:3, Ps 10:13; [[נִאַ֫חְתָּ]] 2Sa 12:14, etc.; Impf. [[יְנׇאֵץ]] Ps 74:10; sf. [[יְנַאֲחֻנִי]] Nu 14:11; Inf. abs. [[נִאֵץ]] (Sta: &#167; 221) 2Sa 12:14; Pt. sf. [[מְנָֽאֲחַי]] Nu 14:23; [[מְנַאֲחַי]] Je 23:17; [[מְנַאֲחָָיִח]] Is 60:14; &#8212;contemn, spurn, subj. men, obj. &#180;[[י]], etc.: Nu 14:11, Nu 14:23, Nu 16:30 (all J), De 31:20, De 1:4 Ps 10:3, Ps 10:13, Je 23:17; obj. &#180;[[שֵׁם י]] Ps 74:10, Ps 74:18; &#180;[[אִמְרַת י]] Is 5:24; &#180;[[מִנְחַת י]] 1Sa 2:17; once obj. Jerus. Is 60:14; cause to contemn (blaspheme AV RV) 2Sa 12:14, 2Sa 12:14 (but [[אׂיְבֵי]] prob. interp.; v. Comm). ","content":"definition","show":"block"},{"title":"Hiph.","body":" Impf. [[יׇנֵ֠אץ]] v. [[נחץ]] ","content":"definition","show":"block"},{"title":"Hithpo(el","body":" Pt. [[כל־היום שְׁמִי מִנּׁאָץ]] Is 52:5 every day is my name contemned.\r","content":"definition","show":"block"}],"notes":"","etymology":[],"morphology":[]}