{"header":{"word":"חֲמוּטַל","entry":3157,"letter":"ח","strongs":2537,"page":327},"definitions":[{"title":"Def","body":" &#134; [[חֲמוּטַל]] Qr, [[חמיטל]] Kt, ","content":"definition","show":"block"},{"title":"n.pr.f.","body":" (meaning dub.; perh., if Kt right, my husband's father is the dew, cf. [[אֲבִיטַל]])&#8212;LXX <span class=\"greek\">Ameitai</span>, <span class=\"greek\">Mitat</span>; A <span class=\"greek\">Amital</span>, <span class=\"greek\">Amitaq</span>, LXXL <span class=\"greek\">Amital</span>;&#8212;mother of the kings Jehoahaz and Zedekiah, sons of Josiah 2Ki 23:31, 2Ki 24:18 Qr (Kt [[חמיטל]]) = Je 52:l Qr (Kt id.)\r","content":"definition","show":"block"}],"notes":"","etymology":[],"morphology":[]}