{"header":{"word":"[נׇוׇה","entry":5959,"letter":"נ","strongs":5115,"page":627},"definitions":[{"title":"Def","body":" &#134; II. [[[נׇוׇה]]] ","content":"definition","show":"block"},{"title":"vb. denom.","body":" dwell, abide (si vera l.);&#8212;only ","content":"definition","show":"block"},{"title":"Qal","body":" Impf. 3 ms. [[לאׁ יִנְוֶה]] Hb Hab 2:5 he shall not adide, so Ke; Hi rest (cf. Da); We prop. [[יִרְוֶה]] be satiated, cf. SyrVer; Krochm [[יׇנוּחַ]].\r","content":"definition","show":"block"}],"notes":"","etymology":[],"morphology":[]}