{"header":{"word":"[חָבָה","entry":2765,"letter":"ח","strongs":2247,"page":285},"definitions":[{"title":"Def","body":" &#134; [[[חָבָה]]] ","content":"definition","show":"block"},{"title":"vb.","body":" withdraw, hide, cf. [[חבא]];&#8212;","content":"definition","show":"block"},{"title":"Qal","body":" Imv. ms. [[חֲבִי]] Is 26:20 (Aram. form, Ol:&#167; 235, 3 Ew:&#167; 224 c Du; Di rds. [[חֲבֵּי]] = [[חֲבֵה]]), withdraw into privacy (&#8214;[[בּאׁ בַחֲדָרֶיךָ]]). ","content":"definition","show":"block"},{"title":"Niph.","body":" Pf. [[וְנֶחְבָּה]] consec. Je 49:10; [[לְנַחְבֵּתֶם]] consec. Jos 2:16 (JE); Inf. [[לְהֵחָבֵה]] (as [[א]]&#147;[[ל]]) 1Ki 22:25, 2Ki 7:12; withdraw, hide oneself, lit. Jos 216 (JE), sq. [[שָׁמָּה]]; 2Ki 7:12 c. [[בְּ]] loc.; 1Ki 22:25; of Esau = Edom, hiding from judgment of &#180;[[י]], [[וְנֶחְבָּה לאׁ יוּכָָּל]] Je 49:10, as pointed, meant no doubt as pf., but constr. then hard; rd. rather inf. abs. [[נַחְבּׂה]]; so Gf Gie al. (v. K&#246;:i. 624).\r","content":"definition","show":"block"}],"notes":"","etymology":[],"morphology":[]}