{"header":{"word":"חִיל","entry":2891,"letter":"ח","strongs":2427,"page":297},"definitions":[{"title":"Def","body":" &#134; [[חִיל]] ","content":"definition","show":"block"},{"title":"n.m.","body":":Ex 15:14 a writhing, anguish;&#8212;&#180;[[ח]] abs. Ex 15:14 + 5 t.&#8212;","content":"definition","show":"block"},{"title":"1.","body":" writhing (contortions of fear) Ex 15:14 (&#8214; vb. [[רָגַז]]). ","content":"definition","show":"block"},{"title":"2.","body":" anguish, always in sim. [[כַּיּוֹלֵדָה]] Ps 48:7 (allied kings against Jerus.); Zion, before Assyrians Mic 4:9; before Scythians or Chaldeans Je 6:24 (&#8214;[[חָרָה]]), = Je 50:43 (of king of Babylon; &#8214;[[חָרָה]]); Je 22:23 (&#8214;[[חבלים]] q.v.)\r","content":"definition","show":"block"}],"notes":"","etymology":[],"morphology":[]}