{"header":{"word":"[מָאַס","entry":4995,"letter":"מ","strongs":3988,"page":549},"definitions":[{"title":"Def","body":" &#134;II. [[[מָאַס]]] ","content":"definition","show":"block"},{"title":"vb. Niph.","body":" flow, run (Aram. id., but rare and dub.;&#8212;secondary form of [[מסס]] q.v.);&#8212;Impf. 3 ms. [[וֶיִּמָּאֵס]] Job 7:5 my skin hath hardened and run (i. e. again, afresh; &#62; GHoffm Du rd. [[וַיִּמַּס]], Bu [[וַיִּמָּאס]], &#8730; [[מסס]]); 3 mpl. [[כְּמוֹ מַיִם יִמָּֽאֲסוּ]] Ps 58:8 (fig. of annihilation of wicked).\r","content":"definition","show":"block"}],"notes":"","etymology":[],"morphology":[]}