{"header":{"word":"מַהְפֶּ֫כֶת","entry":2459,"letter":"ה","strongs":4115,"page":246},"definitions":[{"title":"Def","body":" &#134; [[מַהְפֶּ֫כֶת]] ","content":"definition","show":"block"},{"title":"n.f.","body":" stocks or similar instrum. of punishment (compelling crooked posture, or distorting), mentioned rather late; as punishment for Jeremiah [[אֲשֶׁר בְּשׁׂעַר בִּנְיׇמִן]] &#180;[[הַמּ]] Je 20:2 (LXX <span class=\"greek\">ei(v to\\n katara/kthn k</span>.<span class=\"greek\">t</span>.<span class=\"greek\">l</span>.), cf. &#180;[[אֶל־הַמּ]] Je 29:26 (LXX <span class=\"greek\">ei)v to\\ a)po/kleisma</span>; &#8214;[[אֶל־הַצִּינׁק]], LXX <span class=\"greek\">ei)v to\\n katara/kthn</span>, but order of words perhaps reversed in LXX); [[הַמַּהְפָָּכֶת]] Je 20:3; [[בֵּית הַמַּהְפֶּכֶת]] assigned also to Asa's time 2Ch 16:10 (LXX <span class=\"greek\">ei)v fulakh/n</span>; LXXL <span class=\"greek\">ei)v oi)=kon fulakh=v</span>; cf. Ac 16:24, where <span class=\"greek\">ei)v th\\n e)swte/ran fulakh/n</span>, + <span class=\"greek\">ei)v to\\ cu/lon</span>).\r","content":"definition","show":"block"}],"notes":"","etymology":[],"morphology":[]}