{"header":{"word":"מִשְׂפָּח","entry":6646,"letter":"ס","strongs":4939,"page":705},"definitions":[{"title":"Def","body":" &#134; [[מִשְׂפָּח]] ","content":"definition","show":"block"},{"title":"n.[m.]","body":" prob. outpouring (of blood), bloodshed ([[שׂ]] subst. for [[ס]]; word chosen for assonance with [[מִשְׁפָּט]]);&#8212;abs., [[וַיְקַו]] &#180;[[לְמִשְׁפָּט וְחִנֵּה מ]] Is 5:7 and he waited for justice and lo! bloodshed, so Ges Hi Ew Di Gu Du Che:Comm. Che:Hpt.(dub.).\r","content":"definition","show":"block"}],"notes":"","etymology":[],"morphology":[]}