{"header":{"word":"[מאזן","entry":301,"letter":"א","strongs":3976,"page":24},"definitions":[{"title":"Def","body":" &#134; [[[מאזן]]] ","content":"definition","show":"block"},{"title":"n.[m.] du.","body":" balances, scales (Ar. miyza0nun, Aram. (Nasar.) mawzane0)&#8212;[[מאׁזְנַיִם]] ([[־ָנ֑יִם]]) Is 40:15 + 4 t.; cstr. [[מאׁזְנֵי]] Le 19:36 + 9 t.&#8212;balances, for weighing money Je 32:10 &#180;[[וׇאֶשְׁקׂל הַכֶּסֶף בְּמ]]; hair Ez Eze 5:1 ([[מִשְׁקָל]] &#180;[[מ]]); &#180;[[שַׁחַק מ]]) Is 40:15 dust of bal., sim. of insignif. of nations bef. &#180;[[י]]; fig., calamity Job 6:2; men Ps 62:10; hills Is 40:12 ([[שָׁקַל בַּפֶּלֶס]] &#180;[[הָרִים וּגְבָעוֹת בְּמ]]); [[חֶדֶק]] &#180;[[א]] Le 19:36 (&#8214;&#180;[[אַבְנֵי־ח]], &#180;[[אֵיפַת ח]], &#180;[[הִין ח]]), Ez Eze 45:10 (&#8214;&#180;[[אֵיפַת־ח]], &#180;[[בַּת־ח]]) cf. Pr 16:11 ([[מִשְׁפִּט]] &#180;[[פֶּלֶס וּמ]]); fig. Job 31:6 &#180;[[יִשְׁקְלֵנִי בְּמ]] [[חֶדֶק]]; opp. [[מִרְמָה]] &#180;[[מ]] Pr 11:1 (&#8214;[[אֶבֶן שְׁלֵמָה]]); Pr 20:23 (&#8214;[[אֶבֶן וׇאָָבֶן]]) Am 8:5 (&#8214;[[לְהַקְטִין אֵיפָה וּלְהַגְדִּיל שֶׁקֶל]]) Ho 12:8; [[רֶשַׁע]] &#180;[[מ]] Mic 6:11 (&#8214;[[אַבְנֵי מִרְמָה]]).\r","content":"definition","show":"block"}],"notes":"","etymology":[],"morphology":[]}