{"header":{"word":"עׂז","entry":6949,"letter":"ע","strongs":5797,"page":738},"definitions":[{"title":"Def","body":" &#134; [[עׂז]], and (rarely) [[עוֹז]] ","content":"definition","show":"block"},{"title":"n.m.","body":" strength, might;&#8212;abs. &#180;[[ע]] Ju Jdg 9:51 + , [[עוֹז]] Ps 84:6 +, [[עָז־]] Is 26:1, once [[עָָז]] Ge 49:3; cstr. [[עׂז]] Mic 5:3 + , [[עָז־]] Ps 28:8; sf. [[עָזִּי]] Ex 15:2 + 2 t., [[עֻזִּי]] Ps 28:7 +; [[עָזְְּ]] Ps 21:2 + 2 t., [[עֻזְְּ]] Ps 66:3 + ; sf. 1 pl. [[עוּזֵנוּ]] Ps 81:2; 3 rnpl. [[עֻזׇּמוּ]] Ps 89:18, etc.;&#8212;strength, might (usu. poet., 44 t. PsalmPsalm): ","content":"definition","show":"block"},{"title":"1.","body":" material and physical, [[מִגְדַּל־עׂז]] Ju Jdg 9:51, and fig. (of &#180;[[י]]), Ps 61:4, Pr 18:10, [[מַחֲסִי־עׂז]] Ps 71:7, cf. [[עִיר עָז־לָנוּ]] Is 26:1, [[קִרְיַת־עׂז]] Pr 18:19 (sim.), Pr 10:15 = Pr 18:11 (fig.); [[עׂז מִבְטֶחָָה]] Pr 21:22 (of a city, read poss. [[מעוז]] Toy); [[חוּר עֻזִּי]] Ps 62:8 (fig.); [[מְרוֹם עֻזׇּהּ]] Je 51:53 (of Bab.), [[מַצְּבוֹת עֻזֵּח]] Ez Eze 26:11 (of Tyre), cf. Ps 30:8 (rdg. [[לְהַרְרֵי־עׂז]] Targum Hup Che Kau We; but no obj. for vb.; Gie in Bae prop. [[הָעֳמַדְתִּי]] for [[הֶעֱמַדְתָּה]]); [[רְקִיעַ עֻזּוֹ]] Ps 150:1his mighty firmament (De Hup Kau al.; Ki AV RV Che the f. of his power, where his power dwells); [[בְּכָל־עׂז]] with all one's might 2Sa 6:14 = 1Ch 13:8, + 2Ch 30:21 (where so read, for MT [[כְּלֵי עׂז]], Kau Kit cf. Be Oettli); [[בְּעוֹז]] Pr 31:17, Pr 31:25; abstr. for concr. Ju Jdg 5:21 si vera l., but prob. crpt., cf. GFM Bu; of crocodile Job 41:14; [[קוֹל עׂז]] Ps 68:34 a might voice; [[זְרוֹעַ עֻזּוֹ]] = his mighty arm (fig. of &#180;[[י]]) Is 62:8, cf. Is 51:9, Ps 89:11, Job 26:2, [[גֶּשֶׁם מִטְרוֹת עֻזּוֹ]] Job 37:6; [[מַטֵּה־עׂז]], fig. of political power Je 48:17 (&#8214;[[מַקֵּל תִּפְאָרָה]]), Ez Eze 19:11, Eze 19:12, Eze 19:14 (vine-branches, in fig.), Ps 110:2. ","content":"definition","show":"block"},{"title":"2.","body":" personal, social, and political: ","content":"definition","show":"block"},{"title":"a.","body":" Am 3:11, &#180;[[גְּאוֹן ע]] Le 26:l9 (H), Ez Eze 24:21, Eze 30:6, Eze 30:18, Eze 33:28. ","content":"definition","show":"block"},{"title":"b.","body":" bestowed by &#180;[[י]], 1Sa 2:10 (song), Ps 29:11, Ps 68:36, Ps 86:16, Ps 138:3, [[עוֹז־לוֹ בָָךְ]] Ps 84:6, Ps 138:3; so (implic.) of Zion Is 52:1. ","content":"definition","show":"block"},{"title":" c.","body":" of &#180;[[י]] as strength of his servants Mic 5:3, Is 49:5, Ps 81:2, Ps 84:6, also Ex 15:2 (&#8214;[[יְשׁוּעָה]]) = Is 12:2 = Ps 118:14, cf. Is 45:24, [[עׂז יְשׁוּעָתִי]] Ps 140:8, [[תִּפְאֶרֶת עֻזׇּמוֹ]] Ps 89:18; sts. as their stronghold, for defence Je 16:19 (+ [[מָעֻזִּי]]), Ps 28:7 (+ [[מָגִנִּי]]), v:Ps 28:8 (&#8214;[[מָעוֹז]]), Ps 46:2 (+ [[מַחֲסֶה]]), Ps 59:10 (rdg. [[עֻזִּי]], v. Comm. and Ginsb:marg.; &#8214;[[מִשְׂגַּבִּי]]), v:Ps 59:17 (&#8214; id.), cf. Pr 14:26 (&#8214;[[מַחְסֶה]]); v. also sub ","content":"definition","show":"block"},{"title":"1.","body":"&#8212;Pr 24:5 v. [[עַז]]. ","content":"definition","show":"block"},{"title":"3.","body":" might of &#180;[[י]] (esp. PsalmPsalm): ","content":"definition","show":"block"},{"title":"a.","body":" as essential attribute Hb Hab 3:4, Job 12:16, Ps 62:12, Ps 63:3, Ps 68:35, Ps 93:1, Ps 96:6 = 1Ch 16:27; [[עׂז מֶלֶח]] Ps 99:4 (title of &#180;[[י]]). ","content":"definition","show":"block"},{"title":"b.","body":" theme of ascription in praise Ps 29:1 (c. [[יׇהַב]]) = Ps 96:7 = 1Ch 16:28, Ps 59:17 (c. [[שִׁיר]]), Ps 68:35 (c. [[נׇתַן]]). ","content":"definition","show":"block"},{"title":"c.","body":" exerted for his people and against his foes Ex 15:13 (song), Ps 21:2 (&#8214;[[יְשׁוּעָה]]), v:Ps 21:13, Ps 66:3, Ps 68:29 + v:Ps 68:29 (rdg. [[עוֹז]] for [[עוּזׇּה]], v. [[עזז]]), Ps 74:13, Ps 77:15, Ps 78:26, Ps 105:4 = 1Ch 16:11, Ezr 8:22 (+ [[אַפּוֹ]]), cf. [[עׂז אַפְֶָּ]] Ps 90:11. ","content":"definition","show":"block"},{"title":"d.","body":" manifested in connex. with the ark, [[אֲרוֹן עֻזְֶּ֑]] 2Ch 6:41= Ps 132:8, [[עׂז]] = ark Ps 78:61. ","content":"definition","show":"block"},{"title":"4.","body":" [[עׂז פָּנׇיו]] = boldness, impudence Ec 8:1, changed by wisdom, De Wild al.; &#60; rd. &#180;[[עַז פ]] he who is impudent LXX Siegf (cf. [[עזז]] ","content":"definition","show":"block"},{"title":"Hiph.","body":"). ","content":"definition","show":"block"},{"title":"5.","body":" = stronghold (cf. ","content":"definition","show":"block"},{"title":"2 c","body":"): Ps 8:3 out of the mouth of babes&#133;thou hast founded strength, or a stronghold (for thy defence, cf. v:b), so Ew De Hup Kau Sch Che Dr, cf. Du; &#62; praise Vrss Bae.&#8212;[[מָעוֹז]] v. [[עוז]].\r","content":"definition","show":"block"}],"notes":"","etymology":[],"morphology":[]}