{"header":{"word":"קוֹרֵא","entry":8693,"letter":"ק","strongs":6981,"page":896},"definitions":[{"title":"Def","body":" &#134; II. [[קוֹרֵא]] ","content":"definition","show":"block"},{"title":"n.pr.m.","body":" <span class=\"greek\">Kwrhb</span>, <span class=\"greek\">Kwrh</span>, etc.; Levites: ","content":"definition","show":"block"},{"title":"1.","body":"1Ch 9:19, 1Ch 26:1; ([[קׂרֵא]]); ","content":"definition","show":"block"},{"title":"2.","body":" 2Ch 31:4.\r","content":"definition","show":"block"}],"notes":"","etymology":[],"morphology":[]}